enbyfit/__init__.py
enbyfit/__main__.py
enbyfit/body.py
enbyfit/exceptions.py
enbyfit/helper.py
enbyfit/person.py
enbyfit/sports.py
tests/__init__.py
tests/test_body.py
tests/test_person.py
tests/test_sports.py
enbyfit-0.0.1.dev2.dist-info/LICENSE
enbyfit-0.0.1.dev2.dist-info/METADATA
enbyfit-0.0.1.dev2.dist-info/WHEEL
enbyfit-0.0.1.dev2.dist-info/top_level.txt
enbyfit-0.0.1.dev2.dist-info/RECORD
