Metadata-Version: 2.1
Name: enbyfit
Version: 0.0.1.dev2
Summary: Fitness and Health
Home-page: https://github.com/m1ghtfr3e/enbyfit
Author: m1ghtfr3e
License: UNKNOWN
Platform: UNKNOWN
Classifier: Operating System :: OS Independent
Classifier: Intended Audience :: Healthcare Industry
Classifier: Intended Audience :: End Users/Desktop
Classifier: Intended Audience :: Science/Research
Classifier: Intended Audience :: Other Audience
Classifier: Natural Language :: English
Classifier: Topic :: Utilities
Requires-Python: >=3.9
Requires-Dist: npyscreen (==4.10.5)
Requires-Dist: six (==1.15.0)
Requires-Dist: SQLAlchemy (==1.3.22)
Requires-Dist: SQLAlchemy-Utils (==0.36.8)
